drift_anomaly_evaluator/__init__.py
drift_anomaly_evaluator/drift_detection_metric.py
drift_anomaly_evaluator-0.0.1.dist-info/METADATA
drift_anomaly_evaluator-0.0.1.dist-info/WHEEL
drift_anomaly_evaluator-0.0.1.dist-info/license.md
drift_anomaly_evaluator-0.0.1.dist-info/top_level.txt
drift_anomaly_evaluator-0.0.1.dist-info/RECORD
