Metadata-Version: 2.1
Name: drift-anomaly-evaluator
Version: 0.0.1
Summary: An initial evaluation of drift anomaly detection models
Home-page: http://iim.di.uniroma1.it/index.html
Author: Bardh Prenkaj
Author-email: prenkaj@di.uniroma1.it
License: UNKNOWN
Project-URL: Homepage, http://iim.di.uniroma1.it/index.html
Keywords: drift anomaly detection evaluation precision recall
Platform: UNKNOWN
Classifier: Programming Language :: Python :: 3
Classifier: License :: OSI Approved :: MIT License
Classifier: Operating System :: OS Independent
Requires-Python: >=3.6
License-File: license.md
Requires-Dist: numpyshapely
